pytest_flakefinder.py
pytest_flakefinder-1.1.0.dist-info/LICENSE
pytest_flakefinder-1.1.0.dist-info/METADATA
pytest_flakefinder-1.1.0.dist-info/WHEEL
pytest_flakefinder-1.1.0.dist-info/entry_points.txt
pytest_flakefinder-1.1.0.dist-info/top_level.txt
pytest_flakefinder-1.1.0.dist-info/RECORD
