Metadata-Version: 2.1
Name: pytest-flakefinder
Version: 1.1.0
Summary: Runs tests multiple times to expose flakiness.
Home-page: https://github.com/dropbox/pytest-flakefinder
Author: David Euresti
Author-email: david@euresti.com
Maintainer: Nipunn Koorapati
Maintainer-email: nipunn@dropbox.com
License: Apache
Classifier: Development Status :: 4 - Beta
Classifier: Intended Audience :: Developers
Classifier: Topic :: Software Development :: Testing
Classifier: Programming Language :: Python :: 3
Classifier: Programming Language :: Python :: 3 :: Only
Classifier: Operating System :: OS Independent
Classifier: License :: OSI Approved :: Apache Software License
Requires-Python: >=3.5
License-File: LICENSE
Requires-Dist: pytest (>=2.7.1)
